hello_pip/__init__.py
hello_pip/greet.py
hello_pip_sahil-0.1.0.dist-info/METADATA
hello_pip_sahil-0.1.0.dist-info/WHEEL
hello_pip_sahil-0.1.0.dist-info/top_level.txt
hello_pip_sahil-0.1.0.dist-info/RECORD
