Metadata-Version: 2.4
Name: hello-pip-sahil
Version: 0.1.0
Summary: My first pip package
Author: Sahil
Requires-Python: >=3.7
